[
    {
        "Category": "Fight",
        "League": "Fight",
        "Team 1 Name": "",
        "Team 2 Name": "",
        "Team 1 Logo": "",
        "Team 2 Logo": "",
        "Match Title": "2026 ADCC West Coast Trials",
        "Match Poster": "https://streamed.pk/api/images/proxy/GwZg7AZpYEZgHCAjAJgCzuAQ1sFKBWWYgE0OHjBEx0vmAFNp51JQwHguBOdECYNxD0s-ECEEgSkgMbZs1RhWAQpIGSBjD14tShXBpiLI21H9bcJx7AC8i+SS4Z+rhwRtuS-XfpgOBpwQQA.webp",
        "Match Status": "Live 🔴",
        "Start Time": "11:00 PM | 19-Apr",
        "User-Agent": "Mozilla/5.0 (Windows NT 10.0; Win64; x64)",
        "Streams": [
            {
                "Source": "admin",
                "Stream_No": 1,
                "Language": "English - FloGrappling",
                "Quality": "HD",
                "Embed_URL": "https://embedsports.top/embed/admin/ppv-2026-adcc-west-coast-trials/1"
            },
            {
                "Source": "admin",
                "Stream_No": 2,
                "Language": "English - FloGrappling",
                "Quality": "HD",
                "Embed_URL": "https://embedsports.top/embed/admin/ppv-2026-adcc-west-coast-trials/2"
            },
            {
                "Source": "admin",
                "Stream_No": 3,
                "Language": "English - FloGrappling",
                "Quality": "SD",
                "Embed_URL": "https://embedsports.top/embed/admin/ppv-2026-adcc-west-coast-trials/3"
            }
        ]
    },
    {
        "Category": "Fight",
        "League": "Fight",
        "Team 1 Name": "",
        "Team 2 Name": "",
        "Team 1 Logo": "",
        "Team 2 Logo": "",
        "Match Title": "WrestleMania 42 (Night 2)",
        "Match Poster": "https://streamed.pk/api/images/proxy/GwZg7AZpYEZgHCAjAJgCzuAQ1sFKBWWYgE0OHjBEx0vmAFNp51JQwHguBOdELEBGogAxhRDcQIbIOAlgQoQO4KQJCfxCJJ0iIxlZ9nBiE57JWFMDbhOPYAWx5r5JLhFWuHBGxWcrjvRgHAr6EEA.webp",
        "Match Status": "Live 🔴",
        "Start Time": "04:00 AM | 20-Apr",
        "User-Agent": "Mozilla/5.0 (Windows NT 10.0; Win64; x64)",
        "Streams": [
            {
                "Source": "admin",
                "Stream_No": 1,
                "Language": "English - ESPN Unlimited",
                "Quality": "HD",
                "Embed_URL": "https://embedsports.top/embed/admin/ppv-wrestle-mania-42-night-2/1"
            },
            {
                "Source": "admin",
                "Stream_No": 2,
                "Language": "English - ESPN Unlimited",
                "Quality": "HD",
                "Embed_URL": "https://embedsports.top/embed/admin/ppv-wrestle-mania-42-night-2/2"
            },
            {
                "Source": "admin",
                "Stream_No": 3,
                "Language": "English - ESPN Unlimited",
                "Quality": "SD",
                "Embed_URL": "https://embedsports.top/embed/admin/ppv-wrestle-mania-42-night-2/3"
            },
            {
                "Source": "echo",
                "Stream_No": 1,
                "Language": "",
                "Quality": "HD",
                "Embed_URL": "https://embedsports.top/embed/echo/ppv-event-02-sd-wrestlemania-42-night-2-ppv-02/1"
            },
            {
                "Source": "echo",
                "Stream_No": 2,
                "Language": "",
                "Quality": "HD",
                "Embed_URL": "https://embedsports.top/embed/echo/ppv-event-02-sd-wrestlemania-42-night-2-ppv-02/2"
            },
            {
                "Source": "golf",
                "Stream_No": 1,
                "Language": "English",
                "Quality": "HD",
                "Embed_URL": "https://embedsports.top/embed/golf/21811/1"
            }
        ]
    },
    {
        "Category": "Basketball",
        "League": "Basketball",
        "Team 1 Name": "Detroit Pistons",
        "Team 2 Name": "Orlando Magic",
        "Team 1 Logo": "https://streamed.pk/api/images/proxy/GwZg7AZpYEZgHCAjAJgCzrAThFlBWSUYAUwVmDW2nmAmD32FrWGHXbeAENgBjUgg5sSdTt0z1Rvdqyw8xAkhzD8QfMN2zMQ3EABNcukCRAoQEdSd0EKTPii5gy8IvNGOmtMM7GiIQA.webp",
        "Team 2 Logo": "https://streamed.pk/api/images/proxy/GwZg7AZpYEZgHCAjAJgCzrAThFlBWSUYAUwVmDW2nmAmD32FrWGHXbeAENgBjUgg5sSdTt0z1Rvdqyw8xAkplpJyAExC0c3EHxAQQRlHoO4tICYRjAmfFFzBl4ReaIdNaYJ2NEQgA.webp",
        "Match Title": "Detroit Pistons vs Orlando Magic",
        "Match Poster": "https://streamed.pk/api/images/proxy/GwZg7AZpYEZgHCAjAJgCzrAThFlBWSUYAUwVmDW2nmAmD32FrWGHXbeAENgBjUgg5sSdTtw5kAJqWCEImeuFFs8aEFJAox3MLoghuIPiBJbcIRIgM4SBYEgp9hs+ijArtbD+XpZZ2ky0YB5iohBAA.webp",
        "Match Status": "Live 🔴",
        "Start Time": "04:30 AM | 20-Apr",
        "User-Agent": "Mozilla/5.0 (Windows NT 10.0; Win64; x64)",
        "Streams": [
            {
                "Source": "golf",
                "Stream_No": 1,
                "Language": "English",
                "Quality": "HD",
                "Embed_URL": "https://embedsports.top/embed/golf/21792/1"
            }
        ]
    },
    {
        "Category": "Football",
        "League": "Football",
        "Team 1 Name": "LAFC",
        "Team 2 Name": "San Jose Earthquakes",
        "Team 1 Logo": "",
        "Team 2 Logo": "",
        "Match Title": "LAFC vs. San Jose Earthquakes",
        "Match Poster": "https://streamed.pk/api/images/proxy/GwZg7AZpYEZgHCAjAJgCzuAQ1sFKBWWYgE0OHjBEx0vmAFNp51JQwHguBOdEekiAggYIbsGHcQWCmOrT+IAMZyUIBgqz9gUrcI2iUFRjvVmGRtuE49gBbHmBhySXEqNcOCNuM5H79GAcEiYQQA.webp",
        "Match Status": "Live 🔴",
        "Start Time": "05:00 AM | 20-Apr",
        "User-Agent": "Mozilla/5.0 (Windows NT 10.0; Win64; x64)",
        "Streams": [
            {
                "Source": "admin",
                "Stream_No": 1,
                "Language": "English - MLS",
                "Quality": "HD",
                "Embed_URL": "https://embedsports.top/embed/admin/ppv-lafc-vs-san-jose-earthquakes/1"
            },
            {
                "Source": "admin",
                "Stream_No": 2,
                "Language": "English - MLS",
                "Quality": "HD",
                "Embed_URL": "https://embedsports.top/embed/admin/ppv-lafc-vs-san-jose-earthquakes/2"
            },
            {
                "Source": "admin",
                "Stream_No": 3,
                "Language": "English - MLS",
                "Quality": "SD",
                "Embed_URL": "https://embedsports.top/embed/admin/ppv-lafc-vs-san-jose-earthquakes/3"
            }
        ]
    },
    {
        "Category": "Other",
        "League": "Other",
        "Team 1 Name": "",
        "Team 2 Name": "",
        "Team 1 Logo": "",
        "Team 2 Logo": "",
        "Match Title": "World of Outlaws Sprint Cars Tri State",
        "Match Poster": "https://placehold.co/800x450/1a1a1a/ffffff.png?text=World%20of%20Outlaws%20Sprint%20Cars%20Tri%20State&font=Oswald",
        "Match Status": "Live 🔴",
        "Start Time": "05:15 AM | 20-Apr",
        "User-Agent": "Mozilla/5.0 (Windows NT 10.0; Win64; x64)",
        "Streams": [
            {
                "Source": "echo",
                "Stream_No": 1,
                "Language": "",
                "Quality": "HD",
                "Embed_URL": "https://embedsports.top/embed/echo/ppv-event-05-world-of-outlaws-sprint-cars-tri-state-ppv-05/1"
            },
            {
                "Source": "echo",
                "Stream_No": 2,
                "Language": "",
                "Quality": "HD",
                "Embed_URL": "https://embedsports.top/embed/echo/ppv-event-05-world-of-outlaws-sprint-cars-tri-state-ppv-05/2"
            }
        ]
    },
    {
        "Category": "Baseball",
        "League": "Baseball",
        "Team 1 Name": "Philadelphia Phillies",
        "Team 2 Name": "Atlanta Braves",
        "Team 1 Logo": "https://streamed.pk/api/images/proxy/GwZg7AZpYEZgHCAjAJgCzrAThFlBWSUYAUwVmDW2nmAmD32FrWGHXbeAENgBjUgg5sSdTt0z1Rvdqyw8xAkuhDww4eWDEATENxC79fECVwhzu84wpM+KLmDJr680faa0wjsaIhA.webp",
        "Team 2 Logo": "https://streamed.pk/api/images/proxy/GwZg7AZpYEZgHCAjAJgCzrAThFlBWSUYAUwVmDW2nmAmD32FrWGHXbeAENgBjUgg5sSdTt0z1Rvdqyw8xAkphTAkCEHxAATUiG479mkCYMGIIFDoIUmfVWzBl4ReaNVNaYJ2NEQgA.webp",
        "Match Title": "Philadelphia Phillies vs Atlanta Braves",
        "Match Poster": "https://streamed.pk/api/images/proxy/GwZg7AZpYEZgHCAjAJgCzrAThFlBWSUYAUwVmDW2nmAmD32FrWGHXbeAENgBjUgg5sSdTtw5kAJqWCEImeuFFs8rAAwgoSEKMSJuIPkd0hDiHIhAgUBYEgp9hs+ijAqUXd+XpZZnplowdzFRCCA.webp",
        "Match Status": "Live 🔴",
        "Start Time": "05:20 AM | 20-Apr",
        "User-Agent": "Mozilla/5.0 (Windows NT 10.0; Win64; x64)",
        "Streams": [
            {
                "Source": "admin",
                "Stream_No": 1,
                "Language": "English - Peacock",
                "Quality": "HD",
                "Embed_URL": "https://embedsports.top/embed/admin/ppv-atlanta-braves-vs-philadelphia-phillies/1"
            },
            {
                "Source": "admin",
                "Stream_No": 2,
                "Language": "English - Peacock",
                "Quality": "HD",
                "Embed_URL": "https://embedsports.top/embed/admin/ppv-atlanta-braves-vs-philadelphia-phillies/2"
            },
            {
                "Source": "admin",
                "Stream_No": 3,
                "Language": "English - Peacock",
                "Quality": "SD",
                "Embed_URL": "https://embedsports.top/embed/admin/ppv-atlanta-braves-vs-philadelphia-phillies/3"
            },
            {
                "Source": "delta",
                "Stream_No": 1,
                "Language": "English",
                "Quality": "HD",
                "Embed_URL": "https://embedsports.top/embed/delta/live_mlb_phillies-braves-live-streaming-1200452346/1"
            },
            {
                "Source": "echo",
                "Stream_No": 1,
                "Language": "",
                "Quality": "HD",
                "Embed_URL": "https://embedsports.top/embed/echo/philadelphia-phillies-vs-atlanta-braves-baseball-178328/1"
            },
            {
                "Source": "echo",
                "Stream_No": 2,
                "Language": "",
                "Quality": "HD",
                "Embed_URL": "https://embedsports.top/embed/echo/philadelphia-phillies-vs-atlanta-braves-baseball-178328/2"
            },
            {
                "Source": "golf",
                "Stream_No": 1,
                "Language": "English",
                "Quality": "HD",
                "Embed_URL": "https://embedsports.top/embed/golf/21776/1"
            }
        ]
    },
    {
        "Category": "Hockey",
        "League": "Hockey",
        "Team 1 Name": "Buffalo Sabres",
        "Team 2 Name": "Boston Bruins",
        "Team 1 Logo": "https://streamed.pk/api/images/proxy/GwZg7AZpYEZgHCAjAJgCzrAThFlBWSUYAUwVmDW2nmAmD32FrWGHXbeAENgBjUgg5sSdTt0z1Rvdqyw8xAkuhC1QtJKFghuIACY6QKECVX7zp5YRjAmfFFzBl4ReaIdNaYJ2NEQgA.webp",
        "Team 2 Logo": "https://streamed.pk/api/images/proxy/GwZg7AZpYEZgHCAjAJgCzrAThFlBWSUYAUwVmDW2nmAmD32FrWGHXbeAENgBjUgg5sSdTt0z1Rvdqyw8xAkhxzdsIDQBNSIbiD64QMI4cQ4zBCkz4ouYMvCLzRtprTD2xoiEA.webp",
        "Match Title": "Buffalo Sabres vs Boston Bruins",
        "Match Poster": "https://streamed.pk/api/images/proxy/GwZg7AZpYEZgHCAjAJgCzrAThFlBWSUYAUwVmDW2nmAmD32FrWGHXbeAENgBjUgg5sSdTtw5kAJqWCEImeuFFs8aELTDAwuMH0ghuIPiCkgYIFOcMbTIS0yQU+w2fRRgVKLp-L0sst5Mmp5iohBAA.webp",
        "Match Status": "Live 🔴",
        "Start Time": "05:30 AM | 20-Apr",
        "User-Agent": "Mozilla/5.0 (Windows NT 10.0; Win64; x64)",
        "Streams": [
            {
                "Source": "admin",
                "Stream_No": 1,
                "Language": "English - ESPN",
                "Quality": "HD",
                "Embed_URL": "https://embedsports.top/embed/admin/ppv-boston-bruins-vs-buffalo-sabres/1"
            },
            {
                "Source": "admin",
                "Stream_No": 2,
                "Language": "English - ESPN",
                "Quality": "HD",
                "Embed_URL": "https://embedsports.top/embed/admin/ppv-boston-bruins-vs-buffalo-sabres/2"
            },
            {
                "Source": "admin",
                "Stream_No": 3,
                "Language": "English - ESPN",
                "Quality": "SD",
                "Embed_URL": "https://embedsports.top/embed/admin/ppv-boston-bruins-vs-buffalo-sabres/3"
            },
            {
                "Source": "delta",
                "Stream_No": 1,
                "Language": "English",
                "Quality": "HD",
                "Embed_URL": "https://embedsports.top/embed/delta/live_nhl-playoffs_sabres-bruins-live-streaming-1271051676/1"
            },
            {
                "Source": "delta",
                "Stream_No": 2,
                "Language": "English",
                "Quality": "HD",
                "Embed_URL": "https://embedsports.top/embed/delta/live_nhl-playoffs_sabres-bruins-live-streaming-1271051676/2"
            },
            {
                "Source": "echo",
                "Stream_No": 1,
                "Language": "",
                "Quality": "HD",
                "Embed_URL": "https://embedsports.top/embed/echo/buffalo-sabres-vs-boston-bruins-hockey-424193/1"
            },
            {
                "Source": "echo",
                "Stream_No": 2,
                "Language": "",
                "Quality": "HD",
                "Embed_URL": "https://embedsports.top/embed/echo/buffalo-sabres-vs-boston-bruins-hockey-424193/2"
            },
            {
                "Source": "golf",
                "Stream_No": 1,
                "Language": "English",
                "Quality": "HD",
                "Embed_URL": "https://embedsports.top/embed/golf/21749/1"
            }
        ]
    },
    {
        "Category": "Football",
        "League": "Football",
        "Team 1 Name": "Talleres Cordoba",
        "Team 2 Name": "Deportivo Riestra",
        "Team 1 Logo": "https://streamed.pk/api/images/proxy/GwZg7AZpYEZgHCAjAJgCzuFgpsCwVgBDQhWYNMATkhQFZgrDh49g773hta1gATChUiNiwMOPQjcRLAnQgIIbCH71yDAMbNxPeCKrcCXVmDC58FoA.webp",
        "Team 2 Logo": "https://streamed.pk/api/images/proxy/GwZg7AZpYEZgHCAjAJgCzuFgpsCwVgBDQhWYNMATkhQFZgrDh49g773hta1gATChUiNiwMOPQjcRLAnQgIIAMYh+9cg2XNxPeCKrcCXVmDC58FoA.webp",
        "Match Title": "Talleres Cordoba vs Deportivo Riestra",
        "Match Poster": "https://placehold.co/800x450/1a1a1a/ffffff.png?text=Talleres%20Cordoba%20vs%20Deportivo%20Riestra&font=Oswald",
        "Match Status": "Live 🔴",
        "Start Time": "05:30 AM | 20-Apr",
        "User-Agent": "Mozilla/5.0 (Windows NT 10.0; Win64; x64)",
        "Streams": [
            {
                "Source": "echo",
                "Stream_No": 1,
                "Language": "",
                "Quality": "HD",
                "Embed_URL": "https://embedsports.top/embed/echo/talleres-cordoba-vs-deportivo-riestra-football-1492040/1"
            },
            {
                "Source": "echo",
                "Stream_No": 2,
                "Language": "",
                "Quality": "HD",
                "Embed_URL": "https://embedsports.top/embed/echo/talleres-cordoba-vs-deportivo-riestra-football-1492040/2"
            }
        ]
    },
    {
        "Category": "Basketball",
        "League": "Basketball",
        "Team 1 Name": "San Antonio Spurs",
        "Team 2 Name": "Portland Trail Blazers",
        "Team 1 Logo": "https://streamed.pk/api/images/proxy/GwZg7AZpYEZgHCAjAJgCzrAThFlBWSUYAUwVmDW2nmAmD32FrWGHXbeAENgBjUgg5sSdTt0z1Rvdqyw8xAkhzlhRtXvhDcQAE20GQIEiBTGQiPgQpMrXNeXrzRKYE1pg1Y0RCA.webp",
        "Team 2 Logo": "https://streamed.pk/api/images/proxy/GwZg7AZpYEZgHCAjAJgCzrAThFlBWSUYAUwVmDW2nmAmD32FrWGHXbeAENgBjUgg5sSdTt0z1Rvdqyw8xAkhzDAkwAAx0Q3bDpAATECkMgIZkCWOXjBCkz4ouYMvCLzRTprTAuxoiCA.webp",
        "Match Title": "San Antonio Spurs vs Portland Trail Blazers",
        "Match Poster": "https://streamed.pk/api/images/proxy/GwZg7AZpYEZgHCAjAJgCzrAThFlBWSUYAUwVmDW2nmAmD32FrWGHXbeAENgBjUgg5sSdTtw5kAJqWCEImeuFFs8rHKO5gpYMtxD6+IEiBS4QiREaPwCwJBT7DZ9FLrYouu8vSyzPTLRg7vSiEEA.webp",
        "Match Status": "Live 🔴",
        "Start Time": "07:00 AM | 20-Apr",
        "User-Agent": "Mozilla/5.0 (Windows NT 10.0; Win64; x64)",
        "Streams": [
            {
                "Source": "admin",
                "Stream_No": 1,
                "Language": "English - NBC",
                "Quality": "HD",
                "Embed_URL": "https://embedsports.top/embed/admin/ppv-portland-trail-blazers-vs-san-antonio-spurs/1"
            },
            {
                "Source": "admin",
                "Stream_No": 2,
                "Language": "English - NBC",
                "Quality": "HD",
                "Embed_URL": "https://embedsports.top/embed/admin/ppv-portland-trail-blazers-vs-san-antonio-spurs/2"
            },
            {
                "Source": "admin",
                "Stream_No": 3,
                "Language": "English - NBC",
                "Quality": "SD",
                "Embed_URL": "https://embedsports.top/embed/admin/ppv-portland-trail-blazers-vs-san-antonio-spurs/3"
            },
            {
                "Source": "delta",
                "Stream_No": 1,
                "Language": "English",
                "Quality": "HD",
                "Embed_URL": "https://embedsports.top/embed/delta/live_nba_spurs-trail-blazers-live-streaming-1271214513/1"
            },
            {
                "Source": "echo",
                "Stream_No": 1,
                "Language": "",
                "Quality": "HD",
                "Embed_URL": "https://embedsports.top/embed/echo/san-antonio-spurs-vs-portland-trail-blazers-basketball-497857/1"
            },
            {
                "Source": "echo",
                "Stream_No": 2,
                "Language": "",
                "Quality": "HD",
                "Embed_URL": "https://embedsports.top/embed/echo/san-antonio-spurs-vs-portland-trail-blazers-basketball-497857/2"
            },
            {
                "Source": "echo",
                "Stream_No": 3,
                "Language": "",
                "Quality": "HD",
                "Embed_URL": "https://embedsports.top/embed/echo/san-antonio-spurs-vs-portland-trail-blazers-basketball-497857/3"
            },
            {
                "Source": "golf",
                "Stream_No": 1,
                "Language": "English",
                "Quality": "HD",
                "Embed_URL": "https://embedsports.top/embed/golf/21758/1"
            }
        ]
    },
    {
        "Category": "Football",
        "League": "Football",
        "Team 1 Name": "America de Cali",
        "Team 2 Name": "Millonarios",
        "Team 1 Logo": "https://streamed.pk/api/images/proxy/GwZg7AZpYEZgHCAjAJgCzuFgpsCwVgBDQhWYNMATkhQFZgrDh49g773hta1gATChUiNiwMOPQjcRLAnQgiikIhD1yDAMbNxPeCKrcCXVmDC58FoA.webp",
        "Team 2 Logo": "https://streamed.pk/api/images/proxy/GwZg7AZpYEZgHCAjAJgCzuFgpsCwVgBDQhWYNMATkhQFZgrDh49g773hta1gATChUiNiwMOPQjcRLAnQgiikFRDZ65BgGNm4nvBFVuBLqzBhc+S0A.webp",
        "Match Title": "America de Cali vs Millonarios",
        "Match Poster": "https://placehold.co/800x450/1a1a1a/ffffff.png?text=America%20de%20Cali%20vs%20Millonarios&font=Oswald",
        "Match Status": "Live 🔴",
        "Start Time": "07:30 AM | 20-Apr",
        "User-Agent": "Mozilla/5.0 (Windows NT 10.0; Win64; x64)",
        "Streams": [
            {
                "Source": "echo",
                "Stream_No": 1,
                "Language": "",
                "Quality": "HD",
                "Embed_URL": "https://embedsports.top/embed/echo/america-de-cali-vs-millonarios-football-1506092/1"
            },
            {
                "Source": "echo",
                "Stream_No": 2,
                "Language": "",
                "Quality": "HD",
                "Embed_URL": "https://embedsports.top/embed/echo/america-de-cali-vs-millonarios-football-1506092/2"
            }
        ]
    },
    {
        "Category": "Hockey",
        "League": "Hockey",
        "Team 1 Name": "Vegas Golden Knights",
        "Team 2 Name": "Utah Mammoth",
        "Team 1 Logo": "https://streamed.pk/api/images/proxy/GwZg7AZpYEZgHCAjAJgCzrAThFlBWSUYAUwVmDW2nmAmD32FrWGHXbeAENgBjUgg5sSdTt0z1Rvdqyw8xAkuhACAJnRAQQJXCG4g1+kCh0hERoyBMEKTPii5gy8IvNGOmtMM7GiIQA.webp",
        "Team 2 Logo": "https://streamed.pk/api/images/proxy/GwZg7AZpYEZgHCAjAJgCzrAThFlBWSUYAUwVmDW2nmAmD32FrWGHXbeAENgBjUgg5sSdTt0z1Rvdqyw8xAkpj4hRoebxzcQqiCAAmhkChAwQic-AIUmfFFzBl4ReaIdNaYJ2NEQgA.webp",
        "Match Title": "Vegas Golden Knights vs Utah Mammoth",
        "Match Poster": "https://streamed.pk/api/images/proxy/GwZg7AZpYEZgHCAjAJgCzrAThFlBWSUYAUwVmDW2nmAmD32FrWGHXbeAENgBjUgg5sSdTtw5kAJqWCEImeuFFs8aEOBDApCOiG76QfEFJAwQKM4ZzGSBYEgp9hs+ijAqUXD+XpZZXky0YB5iohBAA.webp",
        "Match Status": "Live 🔴",
        "Start Time": "08:00 AM | 20-Apr",
        "User-Agent": "Mozilla/5.0 (Windows NT 10.0; Win64; x64)",
        "Streams": [
            {
                "Source": "admin",
                "Stream_No": 1,
                "Language": "English - ESPN",
                "Quality": "HD",
                "Embed_URL": "https://embedsports.top/embed/admin/ppv-utah-mammoth-vs-vegas-golden-knights/1"
            },
            {
                "Source": "admin",
                "Stream_No": 2,
                "Language": "English - ESPN",
                "Quality": "HD",
                "Embed_URL": "https://embedsports.top/embed/admin/ppv-utah-mammoth-vs-vegas-golden-knights/2"
            },
            {
                "Source": "admin",
                "Stream_No": 3,
                "Language": "English - ESPN",
                "Quality": "SD",
                "Embed_URL": "https://embedsports.top/embed/admin/ppv-utah-mammoth-vs-vegas-golden-knights/3"
            },
            {
                "Source": "delta",
                "Stream_No": 1,
                "Language": "English",
                "Quality": "HD",
                "Embed_URL": "https://embedsports.top/embed/delta/live_nhl-playoffs_golden-knights-mammoth-live-streaming-1271967759/1"
            },
            {
                "Source": "delta",
                "Stream_No": 2,
                "Language": "English",
                "Quality": "HD",
                "Embed_URL": "https://embedsports.top/embed/delta/live_nhl-playoffs_golden-knights-mammoth-live-streaming-1271967759/2"
            },
            {
                "Source": "echo",
                "Stream_No": 1,
                "Language": "",
                "Quality": "HD",
                "Embed_URL": "https://embedsports.top/embed/echo/vegas-golden-knights-vs-utah-mammoth-hockey-424243/1"
            },
            {
                "Source": "echo",
                "Stream_No": 2,
                "Language": "",
                "Quality": "HD",
                "Embed_URL": "https://embedsports.top/embed/echo/vegas-golden-knights-vs-utah-mammoth-hockey-424243/2"
            },
            {
                "Source": "golf",
                "Stream_No": 1,
                "Language": "English",
                "Quality": "HD",
                "Embed_URL": "https://embedsports.top/embed/golf/21750/1"
            }
        ]
    },
    {
        "Category": "Cricket",
        "League": "Cricket",
        "Team 1 Name": "",
        "Team 2 Name": "",
        "Team 1 Logo": "",
        "Team 2 Logo": "",
        "Match Title": "Willow Cricket",
        "Match Poster": "https://streamed.pk/api/images/proxy/GwZg7AZpYEZgHCAjAJgCzuAQ2C4+cBjYAUwRQFYxi8xg61rLoATdMFSCiUME-YAE5gFbLnrlGUGtB5lBFRvPqVgSWMEJ58fBJCGlxo+BP5zgEIA.webp",
        "Match Status": "Upcoming ⏳",
        "Start Time": "",
        "User-Agent": "Mozilla/5.0 (Windows NT 10.0; Win64; x64)",
        "Streams": [
            {
                "Source": "admin",
                "Stream_No": 1,
                "Language": "English",
                "Quality": "HD",
                "Embed_URL": "https://embedsports.top/embed/admin/admin-willow-cricket/1"
            },
            {
                "Source": "admin",
                "Stream_No": 2,
                "Language": "Willow 2",
                "Quality": "HD",
                "Embed_URL": "https://embedsports.top/embed/admin/admin-willow-cricket/2"
            },
            {
                "Source": "admin",
                "Stream_No": 3,
                "Language": "Willow Sports",
                "Quality": "HD",
                "Embed_URL": "https://embedsports.top/embed/admin/admin-willow-cricket/3"
            },
            {
                "Source": "admin",
                "Stream_No": 4,
                "Language": "English",
                "Quality": "SD",
                "Embed_URL": "https://embedsports.top/embed/admin/admin-willow-cricket/4"
            },
            {
                "Source": "admin",
                "Stream_No": 5,
                "Language": "Willow 2",
                "Quality": "SD",
                "Embed_URL": "https://embedsports.top/embed/admin/admin-willow-cricket/5"
            },
            {
                "Source": "admin",
                "Stream_No": 6,
                "Language": "Willow Sports",
                "Quality": "SD",
                "Embed_URL": "https://embedsports.top/embed/admin/admin-willow-cricket/6"
            }
        ]
    },
    {
        "Category": "Motor-sports",
        "League": "Motor-sports",
        "Team 1 Name": "",
        "Team 2 Name": "",
        "Team 1 Logo": "",
        "Team 2 Logo": "",
        "Match Title": "Rally TV",
        "Match Poster": "https://streamed.pk/api/images/proxy/GwZg7AZpYEZgHCAjAJgCzuMFBWLwBTYCbYAQxSzPzLCWDWB12Hga00quAGNCF0GdCBQhqjEM1Y4AJhixo5YXLCa8uwMAQSRgATkKk8bMFuKGIQA.webp",
        "Match Status": "Upcoming ⏳",
        "Start Time": "",
        "User-Agent": "Mozilla/5.0 (Windows NT 10.0; Win64; x64)",
        "Streams": [
            {
                "Source": "admin",
                "Stream_No": 1,
                "Language": "English",
                "Quality": "HD",
                "Embed_URL": "https://embedsports.top/embed/admin/admin-rally-tv/1"
            }
        ]
    }
]